{
    "id": 1758786644224,
    "rows": 21,
    "cols": 21,
    "elements": [
        {
            "id": "arrow-1",
            "type": "arrow",
            "direction": "left",
            "width": 2,
            "height": 1,
            "position": {
                "x": 10,
                "y": 10
            }
        },
        {
            "id": "arrow-3",
            "type": "arrow",
            "direction": "up",
            "width": 1,
            "height": 2,
            "position": {
                "x": 9,
                "y": 10
            }
        },
        {
            "id": "arrow-4",
            "type": "arrow",
            "direction": "right",
            "width": 2,
            "height": 1,
            "position": {
                "x": 10,
                "y": 11
            }
        },
        {
            "id": "arrow-2",
            "type": "arrow",
            "direction": "right",
            "width": 2,
            "height": 1,
            "position": {
                "x": 9,
                "y": 9
            }
        },
        {
            "id": "arrow-5",
            "type": "arrow",
            "direction": "right",
            "width": 2,
            "height": 1,
            "position": {
                "x": 11,
                "y": 9
            }
        },
        {
            "id": "arrow-7",
            "type": "arrow",
            "direction": "up",
            "width": 1,
            "height": 2,
            "position": {
                "x": 8,
                "y": 10
            }
        },
        {
            "id": "arrow-10",
            "type": "arrow",
            "direction": "left",
            "width": 2,
            "height": 1,
            "position": {
                "x": 10,
                "y": 12
            }
        },
        {
            "id": "arrow-12",
            "type": "arrow",
            "direction": "down",
            "width": 1,
            "height": 2,
            "position": {
                "x": 12,
                "y": 10
            }
        },
        {
            "id": "arrow-9",
            "type": "arrow",
            "direction": "left",
            "width": 2,
            "height": 1,
            "position": {
                "x": 9,
                "y": 8
            }
        },
        {
            "id": "arrow-11",
            "type": "arrow",
            "direction": "left",
            "width": 2,
            "height": 1,
            "position": {
                "x": 11,
                "y": 8
            }
        },
        {
            "id": "arrow-16",
            "type": "arrow",
            "direction": "down",
            "width": 1,
            "height": 2,
            "position": {
                "x": 7,
                "y": 10
            }
        },
        {
            "id": "arrow-6",
            "type": "arrow",
            "direction": "up",
            "width": 1,
            "height": 2,
            "position": {
                "x": 8,
                "y": 8
            }
        },
        {
            "id": "arrow-8",
            "type": "arrow",
            "direction": "left",
            "width": 2,
            "height": 1,
            "position": {
                "x": 8,
                "y": 12
            }
        },
        {
            "id": "arrow-13",
            "type": "arrow",
            "direction": "left",
            "width": 2,
            "height": 1,
            "position": {
                "x": 12,
                "y": 12
            }
        },
        {
            "id": "arrow-19",
            "type": "arrow",
            "direction": "right",
            "width": 2,
            "height": 1,
            "position": {
                "x": 9,
                "y": 7
            }
        },
        {
            "id": "arrow-21",
            "type": "arrow",
            "direction": "right",
            "width": 2,
            "height": 1,
            "position": {
                "x": 11,
                "y": 7
            }
        },
        {
            "id": "arrow-24",
            "type": "arrow",
            "direction": "down",
            "width": 1,
            "height": 2,
            "position": {
                "x": 13,
                "y": 9
            }
        },
        {
            "id": "arrow-25",
            "type": "arrow",
            "direction": "right",
            "width": 2,
            "height": 1,
            "position": {
                "x": 13,
                "y": 11
            }
        },
        {
            "id": "arrow-36",
            "type": "arrow",
            "direction": "up",
            "width": 1,
            "height": 2,
            "position": {
                "x": 10,
                "y": 13
            }
        },
        {
            "id": "arrow-41",
            "type": "arrow",
            "direction": "right",
            "width": 2,
            "height": 1,
            "position": {
                "x": 14,
                "y": 10
            }
        },
        {
            "id": "arrow-15",
            "type": "arrow",
            "direction": "down",
            "width": 1,
            "height": 2,
            "position": {
                "x": 7,
                "y": 8
            }
        },
        {
            "id": "arrow-17",
            "type": "arrow",
            "direction": "down",
            "width": 1,
            "height": 2,
            "position": {
                "x": 7,
                "y": 12
            }
        },
        {
            "id": "arrow-18",
            "type": "arrow",
            "direction": "right",
            "width": 2,
            "height": 1,
            "position": {
                "x": 8,
                "y": 13
            }
        },
        {
            "id": "arrow-22",
            "type": "arrow",
            "direction": "down",
            "width": 1,
            "height": 2,
            "position": {
                "x": 12,
                "y": 13
            }
        },
        {
            "id": "arrow-30",
            "type": "arrow",
            "direction": "up",
            "width": 1,
            "height": 2,
            "position": {
                "x": 6,
                "y": 11
            }
        },
        {
            "id": "arrow-34",
            "type": "arrow",
            "direction": "up",
            "width": 1,
            "height": 2,
            "position": {
                "x": 9,
                "y": 14
            }
        },
        {
            "id": "arrow-55",
            "type": "arrow",
            "direction": "up",
            "width": 1,
            "height": 2,
            "position": {
                "x": 10,
                "y": 5
            }
        },
        {
            "id": "arrow-56",
            "type": "arrow",
            "direction": "up",
            "width": 1,
            "height": 2,
            "position": {
                "x": 10,
                "y": 15
            }
        },
        {
            "id": "arrow-14",
            "type": "arrow",
            "direction": "right",
            "width": 2,
            "height": 1,
            "position": {
                "x": 7,
                "y": 7
            }
        },
        {
            "id": "arrow-23",
            "type": "arrow",
            "direction": "down",
            "width": 1,
            "height": 2,
            "position": {
                "x": 13,
                "y": 7
            }
        },
        {
            "id": "arrow-26",
            "type": "arrow",
            "direction": "left",
            "width": 2,
            "height": 1,
            "position": {
                "x": 13,
                "y": 13
            }
        },
        {
            "id": "arrow-33",
            "type": "arrow",
            "direction": "left",
            "width": 2,
            "height": 1,
            "position": {
                "x": 8,
                "y": 6
            }
        },
        {
            "id": "arrow-40",
            "type": "arrow",
            "direction": "up",
            "width": 1,
            "height": 2,
            "position": {
                "x": 14,
                "y": 8
            }
        },
        {
            "id": "arrow-46",
            "type": "arrow",
            "direction": "right",
            "width": 2,
            "height": 1,
            "position": {
                "x": 5,
                "y": 10
            }
        },
        {
            "id": "arrow-63",
            "type": "arrow",
            "direction": "right",
            "width": 2,
            "height": 1,
            "position": {
                "x": 15,
                "y": 11
            }
        },
        {
            "id": "arrow-28",
            "type": "arrow",
            "direction": "down",
            "width": 1,
            "height": 2,
            "position": {
                "x": 6,
                "y": 7
            }
        },
        {
            "id": "arrow-31",
            "type": "arrow",
            "direction": "up",
            "width": 1,
            "height": 2,
            "position": {
                "x": 6,
                "y": 13
            }
        },
        {
            "id": "arrow-32",
            "type": "arrow",
            "direction": "left",
            "width": 2,
            "height": 1,
            "position": {
                "x": 7,
                "y": 14
            }
        },
        {
            "id": "arrow-38",
            "type": "arrow",
            "direction": "down",
            "width": 1,
            "height": 2,
            "position": {
                "x": 13,
                "y": 14
            }
        },
        {
            "id": "arrow-54",
            "type": "arrow",
            "direction": "up",
            "width": 1,
            "height": 2,
            "position": {
                "x": 8,
                "y": 15
            }
        },
        {
            "id": "arrow-58",
            "type": "arrow",
            "direction": "down",
            "width": 1,
            "height": 2,
            "position": {
                "x": 12,
                "y": 5
            }
        },
        {
            "id": "arrow-62",
            "type": "arrow",
            "direction": "up",
            "width": 1,
            "height": 2,
            "position": {
                "x": 15,
                "y": 8
            }
        },
        {
            "id": "arrow-75",
            "type": "arrow",
            "direction": "up",
            "width": 1,
            "height": 2,
            "position": {
                "x": 9,
                "y": 4
            }
        },
        {
            "id": "arrow-78",
            "type": "arrow",
            "direction": "up",
            "width": 1,
            "height": 2,
            "position": {
                "x": 11,
                "y": 16
            }
        },
        {
            "id": "arrow-95",
            "type": "arrow",
            "direction": "right",
            "width": 2,
            "height": 1,
            "position": {
                "x": 3,
                "y": 10
            }
        },
        {
            "id": "arrow-27",
            "type": "arrow",
            "direction": "left",
            "width": 2,
            "height": 1,
            "position": {
                "x": 6,
                "y": 6
            }
        },
        {
            "id": "arrow-39",
            "type": "arrow",
            "direction": "up",
            "width": 1,
            "height": 2,
            "position": {
                "x": 14,
                "y": 6
            }
        },
        {
            "id": "arrow-43",
            "type": "arrow",
            "direction": "left",
            "width": 2,
            "height": 1,
            "position": {
                "x": 14,
                "y": 14
            }
        },
        {
            "id": "arrow-64",
            "type": "arrow",
            "direction": "left",
            "width": 2,
            "height": 1,
            "position": {
                "x": 15,
                "y": 13
            }
        },
        {
            "id": "arrow-68",
            "type": "arrow",
            "direction": "right",
            "width": 2,
            "height": 1,
            "position": {
                "x": 4,
                "y": 8
            }
        },
        {
            "id": "arrow-70",
            "type": "arrow",
            "direction": "down",
            "width": 1,
            "height": 2,
            "position": {
                "x": 4,
                "y": 12
            }
        },
        {
            "id": "arrow-85",
            "type": "arrow",
            "direction": "right",
            "width": 2,
            "height": 1,
            "position": {
                "x": 16,
                "y": 8
            }
        },
        {
            "id": "arrow-87",
            "type": "arrow",
            "direction": "right",
            "width": 2,
            "height": 1,
            "position": {
                "x": 16,
                "y": 12
            }
        },
        {
            "id": "arrow-112",
            "type": "arrow",
            "direction": "right",
            "width": 2,
            "height": 1,
            "position": {
                "x": 17,
                "y": 9
            }
        },
        {
            "id": "arrow-50",
            "type": "arrow",
            "direction": "left",
            "width": 2,
            "height": 1,
            "position": {
                "x": 6,
                "y": 5
            }
        },
        {
            "id": "arrow-51",
            "type": "arrow",
            "direction": "right",
            "width": 2,
            "height": 1,
            "position": {
                "x": 6,
                "y": 16
            }
        },
        {
            "id": "arrow-60",
            "type": "arrow",
            "direction": "down",
            "width": 1,
            "height": 2,
            "position": {
                "x": 14,
                "y": 15
            }
        },
        {
            "id": "arrow-61",
            "type": "arrow",
            "direction": "up",
            "width": 1,
            "height": 2,
            "position": {
                "x": 15,
                "y": 6
            }
        },
        {
            "id": "arrow-80",
            "type": "arrow",
            "direction": "right",
            "width": 2,
            "height": 1,
            "position": {
                "x": 13,
                "y": 4
            }
        },
        {
            "id": "arrow-44",
            "type": "arrow",
            "direction": "down",
            "width": 1,
            "height": 2,
            "position": {
                "x": 5,
                "y": 5
            }
        },
        {
            "id": "arrow-49",
            "type": "arrow",
            "direction": "down",
            "width": 1,
            "height": 2,
            "position": {
                "x": 5,
                "y": 15
            }
        },
        {
            "id": "arrow-88",
            "type": "arrow",
            "direction": "left",
            "width": 2,
            "height": 1,
            "position": {
                "x": 16,
                "y": 14
            }
        },
        {
            "id": "arrow-106",
            "type": "arrow",
            "direction": "up",
            "width": 1,
            "height": 2,
            "position": {
                "x": 14,
                "y": 2
            }
        },
        {
            "id": "arrow-114",
            "type": "arrow",
            "direction": "left",
            "width": 2,
            "height": 1,
            "position": {
                "x": 17,
                "y": 13
            }
        },
        {
            "id": "arrow-119",
            "type": "arrow",
            "direction": "right",
            "width": 2,
            "height": 1,
            "position": {
                "x": 1,
                "y": 8
            }
        },
        {
            "id": "arrow-121",
            "type": "arrow",
            "direction": "right",
            "width": 2,
            "height": 1,
            "position": {
                "x": 1,
                "y": 12
            }
        },
        {
            "id": "arrow-73",
            "type": "arrow",
            "direction": "left",
            "width": 2,
            "height": 1,
            "position": {
                "x": 5,
                "y": 4
            }
        },
        {
            "id": "arrow-82",
            "type": "arrow",
            "direction": "up",
            "width": 1,
            "height": 2,
            "position": {
                "x": 15,
                "y": 4
            }
        },
        {
            "id": "arrow-107",
            "type": "arrow",
            "direction": "down",
            "width": 1,
            "height": 2,
            "position": {
                "x": 14,
                "y": 17
            }
        },
        {
            "id": "arrow-111",
            "type": "arrow",
            "direction": "left",
            "width": 2,
            "height": 1,
            "position": {
                "x": 17,
                "y": 6
            }
        },
        {
            "id": "arrow-129",
            "type": "arrow",
            "direction": "up",
            "width": 1,
            "height": 2,
            "position": {
                "x": 7,
                "y": 1
            }
        },
        {
            "id": "arrow-130",
            "type": "arrow",
            "direction": "up",
            "width": 1,
            "height": 2,
            "position": {
                "x": 7,
                "y": 18
            }
        },
        {
            "id": "arrow-66",
            "type": "arrow",
            "direction": "down",
            "width": 1,
            "height": 2,
            "position": {
                "x": 4,
                "y": 4
            }
        },
        {
            "id": "arrow-108",
            "type": "arrow",
            "direction": "up",
            "width": 1,
            "height": 2,
            "position": {
                "x": 16,
                "y": 2
            }
        },
        {
            "id": "arrow-118",
            "type": "arrow",
            "direction": "right",
            "width": 2,
            "height": 1,
            "position": {
                "x": 1,
                "y": 6
            }
        },
        {
            "id": "arrow-122",
            "type": "arrow",
            "direction": "left",
            "width": 2,
            "height": 1,
            "position": {
                "x": 1,
                "y": 15
            }
        },
        {
            "id": "arrow-128",
            "type": "arrow",
            "direction": "up",
            "width": 1,
            "height": 2,
            "position": {
                "x": 6,
                "y": 18
            }
        },
        {
            "id": "arrow-98",
            "type": "arrow",
            "direction": "right",
            "width": 2,
            "height": 1,
            "position": {
                "x": 3,
                "y": 17
            }
        },
        {
            "id": "arrow-109",
            "type": "arrow",
            "direction": "down",
            "width": 1,
            "height": 2,
            "position": {
                "x": 16,
                "y": 17
            }
        },
        {
            "id": "arrow-127",
            "type": "arrow",
            "direction": "down",
            "width": 1,
            "height": 2,
            "position": {
                "x": 5,
                "y": 1
            }
        },
        {
            "id": "arrow-91",
            "type": "arrow",
            "direction": "left",
            "width": 2,
            "height": 1,
            "position": {
                "x": 3,
                "y": 3
            }
        },
        {
            "id": "arrow-110",
            "type": "arrow",
            "direction": "down",
            "width": 1,
            "height": 2,
            "position": {
                "x": 17,
                "y": 3
            }
        },
        {
            "id": "arrow-115",
            "type": "arrow",
            "direction": "down",
            "width": 1,
            "height": 2,
            "position": {
                "x": 17,
                "y": 17
            }
        },
        {
            "id": "arrow-117",
            "type": "arrow",
            "direction": "left",
            "width": 2,
            "height": 1,
            "position": {
                "x": 1,
                "y": 4
            }
        },
        {
            "id": "arrow-126",
            "type": "arrow",
            "direction": "left",
            "width": 2,
            "height": 1,
            "position": {
                "x": 4,
                "y": 18
            }
        },
        {
            "id": "arrow-125",
            "type": "arrow",
            "direction": "left",
            "width": 2,
            "height": 1,
            "position": {
                "x": 3,
                "y": 2
            }
        },
        {
            "id": "arrow-116",
            "type": "arrow",
            "direction": "down",
            "width": 1,
            "height": 2,
            "position": {
                "x": 2,
                "y": 2
            }
        },
        {
            "id": "arrow-124",
            "type": "arrow",
            "direction": "up",
            "width": 1,
            "height": 2,
            "position": {
                "x": 2,
                "y": 18
            }
        },
        {
            "id": "arrow-refill-89",
            "type": "arrow",
            "direction": "up",
            "width": 1,
            "height": 2,
            "position": {
                "x": 11,
                "y": 13
            }
        },
        {
            "id": "arrow-refill-90",
            "type": "arrow",
            "direction": "right",
            "width": 2,
            "height": 1,
            "position": {
                "x": 5,
                "y": 9
            }
        },
        {
            "id": "arrow-refill-91",
            "type": "arrow",
            "direction": "down",
            "width": 1,
            "height": 2,
            "position": {
                "x": 5,
                "y": 11
            }
        },
        {
            "id": "arrow-refill-92",
            "type": "arrow",
            "direction": "down",
            "width": 1,
            "height": 2,
            "position": {
                "x": 5,
                "y": 13
            }
        },
        {
            "id": "arrow-refill-93",
            "type": "arrow",
            "direction": "left",
            "width": 2,
            "height": 1,
            "position": {
                "x": 6,
                "y": 15
            }
        },
        {
            "id": "arrow-refill-94",
            "type": "arrow",
            "direction": "down",
            "width": 1,
            "height": 2,
            "position": {
                "x": 11,
                "y": 5
            }
        },
        {
            "id": "arrow-refill-95",
            "type": "arrow",
            "direction": "right",
            "width": 2,
            "height": 1,
            "position": {
                "x": 11,
                "y": 15
            }
        },
        {
            "id": "arrow-refill-96",
            "type": "arrow",
            "direction": "left",
            "width": 2,
            "height": 1,
            "position": {
                "x": 13,
                "y": 5
            }
        },
        {
            "id": "arrow-refill-97",
            "type": "arrow",
            "direction": "down",
            "width": 1,
            "height": 2,
            "position": {
                "x": 15,
                "y": 15
            }
        },
        {
            "id": "arrow-refill-98",
            "type": "arrow",
            "direction": "down",
            "width": 1,
            "height": 2,
            "position": {
                "x": 4,
                "y": 6
            }
        },
        {
            "id": "arrow-refill-99",
            "type": "arrow",
            "direction": "down",
            "width": 1,
            "height": 2,
            "position": {
                "x": 4,
                "y": 14
            }
        },
        {
            "id": "arrow-refill-100",
            "type": "arrow",
            "direction": "left",
            "width": 2,
            "height": 1,
            "position": {
                "x": 7,
                "y": 4
            }
        },
        {
            "id": "arrow-refill-101",
            "type": "arrow",
            "direction": "up",
            "width": 1,
            "height": 2,
            "position": {
                "x": 9,
                "y": 16
            }
        },
        {
            "id": "arrow-refill-102",
            "type": "arrow",
            "direction": "right",
            "width": 2,
            "height": 1,
            "position": {
                "x": 11,
                "y": 4
            }
        },
        {
            "id": "arrow-refill-103",
            "type": "arrow",
            "direction": "down",
            "width": 1,
            "height": 2,
            "position": {
                "x": 12,
                "y": 16
            }
        },
        {
            "id": "arrow-refill-104",
            "type": "arrow",
            "direction": "down",
            "width": 1,
            "height": 2,
            "position": {
                "x": 13,
                "y": 16
            }
        },
        {
            "id": "arrow-refill-105",
            "type": "arrow",
            "direction": "up",
            "width": 1,
            "height": 2,
            "position": {
                "x": 16,
                "y": 4
            }
        },
        {
            "id": "arrow-refill-106",
            "type": "arrow",
            "direction": "up",
            "width": 1,
            "height": 2,
            "position": {
                "x": 16,
                "y": 6
            }
        },
        {
            "id": "arrow-refill-107",
            "type": "arrow",
            "direction": "up",
            "width": 1,
            "height": 2,
            "position": {
                "x": 16,
                "y": 9
            }
        },
        {
            "id": "arrow-refill-108",
            "type": "arrow",
            "direction": "left",
            "width": 2,
            "height": 1,
            "position": {
                "x": 16,
                "y": 15
            }
        },
        {
            "id": "arrow-refill-109",
            "type": "arrow",
            "direction": "right",
            "width": 2,
            "height": 1,
            "position": {
                "x": 16,
                "y": 16
            }
        },
        {
            "id": "arrow-refill-110",
            "type": "arrow",
            "direction": "up",
            "width": 1,
            "height": 2,
            "position": {
                "x": 3,
                "y": 4
            }
        },
        {
            "id": "arrow-refill-111",
            "type": "arrow",
            "direction": "up",
            "width": 1,
            "height": 2,
            "position": {
                "x": 3,
                "y": 6
            }
        },
        {
            "id": "arrow-refill-112",
            "type": "arrow",
            "direction": "up",
            "width": 1,
            "height": 2,
            "position": {
                "x": 3,
                "y": 8
            }
        },
        {
            "id": "arrow-refill-113",
            "type": "arrow",
            "direction": "up",
            "width": 1,
            "height": 2,
            "position": {
                "x": 3,
                "y": 11
            }
        },
        {
            "id": "arrow-refill-114",
            "type": "arrow",
            "direction": "up",
            "width": 1,
            "height": 2,
            "position": {
                "x": 3,
                "y": 13
            }
        },
        {
            "id": "arrow-refill-115",
            "type": "arrow",
            "direction": "up",
            "width": 1,
            "height": 2,
            "position": {
                "x": 3,
                "y": 15
            }
        },
        {
            "id": "arrow-refill-116",
            "type": "arrow",
            "direction": "left",
            "width": 2,
            "height": 1,
            "position": {
                "x": 5,
                "y": 3
            }
        },
        {
            "id": "arrow-refill-117",
            "type": "arrow",
            "direction": "right",
            "width": 2,
            "height": 1,
            "position": {
                "x": 5,
                "y": 17
            }
        },
        {
            "id": "arrow-refill-118",
            "type": "arrow",
            "direction": "left",
            "width": 2,
            "height": 1,
            "position": {
                "x": 7,
                "y": 3
            }
        },
        {
            "id": "arrow-refill-119",
            "type": "arrow",
            "direction": "right",
            "width": 2,
            "height": 1,
            "position": {
                "x": 7,
                "y": 17
            }
        },
        {
            "id": "arrow-refill-120",
            "type": "arrow",
            "direction": "left",
            "width": 2,
            "height": 1,
            "position": {
                "x": 9,
                "y": 3
            }
        },
        {
            "id": "arrow-refill-121",
            "type": "arrow",
            "direction": "up",
            "width": 1,
            "height": 2,
            "position": {
                "x": 10,
                "y": 17
            }
        },
        {
            "id": "arrow-refill-122",
            "type": "arrow",
            "direction": "left",
            "width": 2,
            "height": 1,
            "position": {
                "x": 11,
                "y": 3
            }
        },
        {
            "id": "arrow-refill-123",
            "type": "arrow",
            "direction": "down",
            "width": 1,
            "height": 2,
            "position": {
                "x": 15,
                "y": 17
            }
        },
        {
            "id": "arrow-refill-124",
            "type": "arrow",
            "direction": "left",
            "width": 2,
            "height": 1,
            "position": {
                "x": 17,
                "y": 5
            }
        },
        {
            "id": "arrow-refill-125",
            "type": "arrow",
            "direction": "left",
            "width": 2,
            "height": 1,
            "position": {
                "x": 17,
                "y": 7
            }
        },
        {
            "id": "arrow-refill-126",
            "type": "arrow",
            "direction": "right",
            "width": 2,
            "height": 1,
            "position": {
                "x": 17,
                "y": 10
            }
        },
        {
            "id": "arrow-refill-127",
            "type": "arrow",
            "direction": "right",
            "width": 2,
            "height": 1,
            "position": {
                "x": 17,
                "y": 11
            }
        },
        {
            "id": "arrow-refill-128",
            "type": "arrow",
            "direction": "up",
            "width": 1,
            "height": 2,
            "position": {
                "x": 2,
                "y": 9
            }
        },
        {
            "id": "arrow-refill-129",
            "type": "arrow",
            "direction": "down",
            "width": 1,
            "height": 2,
            "position": {
                "x": 2,
                "y": 13
            }
        },
        {
            "id": "arrow-refill-130",
            "type": "arrow",
            "direction": "up",
            "width": 1,
            "height": 2,
            "position": {
                "x": 3,
                "y": 18
            }
        }
    ]
}
